Segmentfault2015YouxiuWenzhangWutu/README.md
Segmentfault2015YouxiuWenzhangWutu/__init__.py
Segmentfault2015YouxiuWenzhangWutu/__main__.py
Segmentfault2015YouxiuWenzhangWutu/file.epub
Segmentfault2015YouxiuWenzhangWutu/index.html
Segmentfault2015YouxiuWenzhangWutu/css/__init__.py
Segmentfault2015YouxiuWenzhangWutu/css/annotations.css
Segmentfault2015YouxiuWenzhangWutu/css/main.css
Segmentfault2015YouxiuWenzhangWutu/css/normalize.css
Segmentfault2015YouxiuWenzhangWutu/css/popup.css
Segmentfault2015YouxiuWenzhangWutu/font/__init__.py
Segmentfault2015YouxiuWenzhangWutu/font/fontello.eot
Segmentfault2015YouxiuWenzhangWutu/font/fontello.svg
Segmentfault2015YouxiuWenzhangWutu/font/fontello.ttf
Segmentfault2015YouxiuWenzhangWutu/font/fontello.woff
Segmentfault2015YouxiuWenzhangWutu/img/__init__.py
Segmentfault2015YouxiuWenzhangWutu/img/annotator-glyph-sprite.png
Segmentfault2015YouxiuWenzhangWutu/img/annotator-icon-sprite.png
Segmentfault2015YouxiuWenzhangWutu/img/apple-touch-icon.png
Segmentfault2015YouxiuWenzhangWutu/img/cancelfullscreen.png
Segmentfault2015YouxiuWenzhangWutu/img/close.png
Segmentfault2015YouxiuWenzhangWutu/img/fullscreen.png
Segmentfault2015YouxiuWenzhangWutu/img/loader.gif
Segmentfault2015YouxiuWenzhangWutu/img/menu-icon.png
Segmentfault2015YouxiuWenzhangWutu/img/save.png
Segmentfault2015YouxiuWenzhangWutu/img/saved.png
Segmentfault2015YouxiuWenzhangWutu/img/settings-s.png
Segmentfault2015YouxiuWenzhangWutu/img/settings.png
Segmentfault2015YouxiuWenzhangWutu/img/star.png
Segmentfault2015YouxiuWenzhangWutu/js/__init__.py
Segmentfault2015YouxiuWenzhangWutu/js/epub.js
Segmentfault2015YouxiuWenzhangWutu/js/epub.min.js
Segmentfault2015YouxiuWenzhangWutu/js/epub.min.map
Segmentfault2015YouxiuWenzhangWutu/js/hooks.min.js
Segmentfault2015YouxiuWenzhangWutu/js/hooks.min.map
Segmentfault2015YouxiuWenzhangWutu/js/reader.js
Segmentfault2015YouxiuWenzhangWutu/js/reader.js.map
Segmentfault2015YouxiuWenzhangWutu/js/reader.min.js
segmentfault_2015_youxiu_wenzhang_wutu-2024.3.1.0.dist-info/METADATA
segmentfault_2015_youxiu_wenzhang_wutu-2024.3.1.0.dist-info/WHEEL
segmentfault_2015_youxiu_wenzhang_wutu-2024.3.1.0.dist-info/entry_points.txt
segmentfault_2015_youxiu_wenzhang_wutu-2024.3.1.0.dist-info/top_level.txt
segmentfault_2015_youxiu_wenzhang_wutu-2024.3.1.0.dist-info/RECORD
